samovar/__init__.py
samovar/ast.py
samovar/database.py
samovar/main.py
samovar/parser.py
samovar/randomness.py
samovar/scanner.py
samovar/terms.py
samovar/tests.py
samovar/generators/__init__.py
samovar/generators/base.py
samovar/generators/breadthfirst.py
samovar/generators/depthfirst.py
samovar/generators/stochastic.py
samovar_py-0.6.dist-info/METADATA
samovar_py-0.6.dist-info/WHEEL
samovar_py-0.6.dist-info/entry_points.txt
samovar_py-0.6.dist-info/top_level.txt
samovar_py-0.6.dist-info/RECORD
