Metadata-Version: 2.1
Name: samovar-py
Version: 0.6
Summary: Samovar: model worlds using propositions and run simulations in them
Author-email: Chris Pressey <packages@catseye.tc>
License: This is free and unencumbered software released into the public domain.
Project-URL: website, https://catseye.tc/node/Samovar
Classifier: License :: OSI Approved :: The Unlicense (Unlicense)
Classifier: Operating System :: OS Independent
Classifier: Programming Language :: Python :: 2.7
Classifier: Programming Language :: Python :: 3
Classifier: Topic :: Artistic Software
Classifier: Topic :: Games/Entertainment :: Simulation
Requires-Python: >=2.7,>=3.5
